ui_manager/__init__.py
ui_manager/resources/themes/dark.qss
ui_manager/resources/themes/light.qss
ui_manager-0.2.0.dist-info/LICENSE.txt
ui_manager-0.2.0.dist-info/METADATA
ui_manager-0.2.0.dist-info/WHEEL
ui_manager-0.2.0.dist-info/top_level.txt
ui_manager-0.2.0.dist-info/RECORD
